{
  "codecNamespace": "coursier.lmcoursier",
  "types": [
    {
      "name": "CoursierConfiguration",
      "namespace": "coursier.lmcoursier",
      "target": "Scala",
      "type": "record",
      "fields": [
        { 
          "name": "log",
          "type": "xsbti.Logger?",
          "default": "None",
          "since": "0.0.1"
        },
        { 
          "name": "resolvers",
          "type": "sbt.librarymanagement.Resolver*",
          "default": "sbt.librarymanagement.Resolver.defaults",
          "since": "0.0.1"
        },
        {
          "name": "reorderResolvers",
          "type": "Boolean",
          "default": "true",
          "since": "0.0.1"
        },
        {
          "name": "parallelDownloads",
          "type": "Int",
          "default": "6",
          "since": "0.0.1"
        },
        {
          "name": "maxIterations",
          "type": "Int",
          "default": "100",
          "since": "0.0.1"
        },
        {
          "name": "sbtScalaOrganization",
          "type": "String?",
          "default": "None",
          "since": "0.0.1"
        },
        {
          "name": "sbtScalaVersion",
          "type": "String?",
          "default": "None",
          "since": "0.0.1"
        },
        {
          "name": "sbtScalaJars",
          "type": "java.io.File*",
          "default": "Vector.empty",
          "since": "0.0.1"
        },
        {
          "name": "interProjectDependencies",
          "type": "coursier.core.Project*",
          "default": "Vector.empty",
          "since": "0.0.1"
        },
        {
          "name": "excludeDependencies",
          "type": "(String, String)*",
          "default": "Vector.empty",
          "since": "0.0.1"
        },
        {
          "name": "fallbackDependencies",
          "type": "coursier.lmcoursier.FallbackDependency*",
          "default": "Vector.empty",
          "since": "0.0.1"
        }
      ]
    }
  ]
}
